{
  "name": "Everforest Light",
  "author": "Márcio Sobel (https://github.com/marciosobel)",
  "scheme_type": "scheme-tonal-spot",
  "colors": {
    "primary": {
      "dark": {
        "color": "#3a94c5"
      },
      "light": {
        "color": "#B4DCF6"
      }
    },
    "on_primary": {
      "dark": {
        "color": "#FFFFFF"
      },
      "light": {
        "color": "#0070A2"
      }
    },
    "primary_container": {
      "dark": {
        "color": "#D5EEFD"
      },
      "light": {
        "color": "#1682B4"
      }
    },
    "on_primary_container": {
      "dark": {
        "color": "#1682B4"
      },
      "light": {
        "color": "#D5EEFD"
      }
    },
    "primary_fixed": {
      "dark": {
        "color": "#D5EEFD"
      },
      "light": {
        "color": "#D5EEFD"
      }
    },
    "primary_fixed_dim": {
      "dark": {
        "color": "#B4DCF6"
      },
      "light": {
        "color": "#B4DCF6"
      }
    },
    "on_primary_fixed": {
      "dark": {
        "color": "#002749"
      },
      "light": {
        "color": "#002749"
      }
    },
    "on_primary_fixed_variant": {
      "dark": {
        "color": "#1682B4"
      },
      "light": {
        "color": "#1682B4"
      }
    },
    "secondary": {
      "dark": {
        "color": "#df69ba"
      },
      "light": {
        "color": "#FFC7EC"
      }
    },
    "on_secondary": {
      "dark": {
        "color": "#FFFFFF"
      },
      "light": {
        "color": "#BA3295"
      }
    },
    "secondary_container": {
      "dark": {
        "color": "#FFE0F7"
      },
      "light": {
        "color": "#CD4DA8"
      }
    },
    "on_secondary_container": {
      "dark": {
        "color": "#CD4DA8"
      },
      "light": {
        "color": "#FFE0F7"
      }
    },
    "secondary_fixed": {
      "dark": {
        "color": "#FFE0F7"
      },
      "light": {
        "color": "#FFE0F7"
      }
    },
    "secondary_fixed_dim": {
      "dark": {
        "color": "#FFC7EC"
      },
      "light": {
        "color": "#FFC7EC"
      }
    },
    "on_secondary_fixed": {
      "dark": {
        "color": "#55003F"
      },
      "light": {
        "color": "#55003F"
      }
    },
    "on_secondary_fixed_variant": {
      "dark": {
        "color": "#CD4DA8"
      },
      "light": {
        "color": "#CD4DA8"
      }
    },
    "tertiary": {
      "dark": {
        "color": "#8da101"
      },
      "light": {
        "color": "#D5E1A9"
      }
    },
    "on_tertiary": {
      "dark": {
        "color": "#FFFFFF"
      },
      "light": {
        "color": "#687B00"
      }
    },
    "tertiary_container": {
      "dark": {
        "color": "#E8F0CE"
      },
      "light": {
        "color": "#7A8D00"
      }
    },
    "on_tertiary_container": {
      "dark": {
        "color": "#7A8D00"
      },
      "light": {
        "color": "#E8F0CE"
      }
    },
    "tertiary_fixed": {
      "dark": {
        "color": "#E8F0CE"
      },
      "light": {
        "color": "#E8F0CE"
      }
    },
    "tertiary_fixed_dim": {
      "dark": {
        "color": "#D5E1A9"
      },
      "light": {
        "color": "#D5E1A9"
      }
    },
    "on_tertiary_fixed": {
      "dark": {
        "color": "#232C00"
      },
      "light": {
        "color": "#232C00"
      }
    },
    "on_tertiary_fixed_variant": {
      "dark": {
        "color": "#7A8D00"
      },
      "light": {
        "color": "#7A8D00"
      }
    },
    "error": {
      "dark": {
        "color": "#f85552"
      },
      "light": {
        "color": "#FFC2BA"
      }
    },
    "on_error": {
      "dark": {
        "color": "#FFFFFF"
      },
      "light": {
        "color": "#D3001F"
      }
    },
    "error_container": {
      "dark": {
        "color": "#FFDDD8"
      },
      "light": {
        "color": "#E73238"
      }
    },
    "on_error_container": {
      "dark": {
        "color": "#E73238"
      },
      "light": {
        "color": "#FFDDD8"
      }
    },
    "background": {
      "dark": {
        "color": "#f8f5e4"
      },
      "light": {
        "color": "#3C464B"
      }
    },
    "on_background": {
      "dark": {
        "color": "#5c6a72"
      },
      "light": {
        "color": "#C1C4BB"
      }
    },
    "surface": {
      "dark": {
        "color": "#f8f5e4"
      },
      "light": {
        "color": "#3C464B"
      }
    },
    "on_surface": {
      "dark": {
        "color": "#5c6a72"
      },
      "light": {
        "color": "#D7D7CB"
      }
    },
    "surface_variant": {
      "dark": {
        "color": "#edeada"
      },
      "light": {
        "color": "#5c6a72"
      }
    },
    "on_surface_variant": {
      "dark": {
        "color": "#6F7B80"
      },
      "light": {
        "color": "#ACB1AC"
      }
    },
    "surface_dim": {
      "dark": {
        "color": "#edeada"
      },
      "light": {
        "color": "#1F2428"
      }
    },
    "surface_bright": {
      "dark": {
        "color": "#fffbef"
      },
      "light": {
        "color": "#5c6a72"
      }
    },
    "surface_container_lowest": {
      "dark": {
        "color": "#fffbef"
      },
      "light": {
        "color": "#1F2428"
      }
    },
    "surface_container_low": {
      "dark": {
        "color": "#f8f5e4"
      },
      "light": {
        "color": "#3C464B"
      }
    },
    "surface_container": {
      "dark": {
        "color": "#edeada"
      },
      "light": {
        "color": "#5c6a72"
      }
    },
    "surface_container_high": {
      "dark": {
        "color": "#D7D7CB"
      },
      "light": {
        "color": "#667379"
      }
    },
    "surface_container_highest": {
      "dark": {
        "color": "#C1C4BB"
      },
      "light": {
        "color": "#6F7B80"
      }
    },
    "surface_tint": {
      "dark": {
        "color": "#3a94c5"
      },
      "light": {
        "color": "#B4DCF6"
      }
    },
    "inverse_surface": {
      "dark": {
        "color": "#5c6a72"
      },
      "light": {
        "color": "#D7D7CB"
      }
    },
    "inverse_on_surface": {
      "dark": {
        "color": "#f8f5e4"
      },
      "light": {
        "color": "#3C464B"
      }
    },
    "inverse_primary": {
      "dark": {
        "color": "#B4DCF6"
      },
      "light": {
        "color": "#3a94c5"
      }
    },
    "outline": {
      "dark": {
        "color": "#838D8F"
      },
      "light": {
        "color": "#979F9D"
      }
    },
    "outline_variant": {
      "dark": {
        "color": "#edeada"
      },
      "light": {
        "color": "#5c6a72"
      }
    },
    "shadow": {
      "dark": {
        "color": "#000000"
      },
      "light": {
        "color": "#000000"
      }
    },
    "scrim": {
      "dark": {
        "color": "#000000"
      },
      "light": {
        "color": "#000000"
      }
    },
    "source_color": {
      "dark": {
        "color": "#3a94c5"
      },
      "light": {
        "color": "#B4DCF6"
      }
    }
  },
  "accents": {
    "default": "accent4",
    "available": {
      "accent1": "#dfa000",
      "accent2": "#8da101",
      "accent3": "#35a77c",
      "accent4": "#3a94c5",
      "accent5": "#df69ba",
      "accent6": "#829181",
      "accent7": "#f57d26",
      "accent8": "#f85552",
      "accent9": "#272e33",
      "accent10": "#414b50"
    }
  }
}
